risingwave_pipeline_sdk/__init__.py
risingwave_pipeline_sdk/client.py
risingwave_pipeline_sdk/models.py
risingwave_pipeline_sdk/pipeline_builder.py
risingwave_pipeline_sdk/discovery/__init__.py
risingwave_pipeline_sdk/discovery/base.py
risingwave_pipeline_sdk/sinks/__init__.py
risingwave_pipeline_sdk/sinks/base.py
risingwave_pipeline_sdk/sinks/iceberg.py
risingwave_pipeline_sdk/sinks/postgresql.py
risingwave_pipeline_sdk/sinks/s3.py
risingwave_pipeline_sdk/sources/__init__.py
risingwave_pipeline_sdk/sources/postgresql.py
risingwave_pipeline_sdk-0.1.1.dist-info/METADATA
risingwave_pipeline_sdk-0.1.1.dist-info/WHEEL
risingwave_pipeline_sdk-0.1.1.dist-info/licenses/LICENSE
risingwave_pipeline_sdk-0.1.1.dist-info/RECORD
