Metadata-Version: 2.4
Name: risingwave-pipeline-sdk
Version: 0.1.1
Summary: A Python SDK for building RisingWave data pipelines with PostgreSQL CDC and multiple sink destinations
Project-URL: Homepage, https://github.com/risingwavelabs/risingwave-pipeline-sdk
Project-URL: Repository, https://github.com/risingwavelabs/risingwave-pipeline-sdk
Project-URL: Issues, https://github.com/risingwavelabs/risingwave-pipeline-sdk/issues
Author-email: Yuxuan Liao <yuxuan@risingwave-labs.com>
License-Expression: Apache-2.0
License-File: LICENSE
Keywords: cdc,data-pipeline,iceberg,postgresql,risingwave,risingwave-pipeline-sdk,risingwave_pipeline_sdk,s3,streaming
Classifier: Development Status :: 4 - Beta
Classifier: Intended Audience :: Developers
Classifier: License :: OSI Approved :: Apache Software License
Classifier: Operating System :: OS Independent
Classifier: Programming Language :: Python :: 3
Classifier: Programming Language :: Python :: 3.10
Classifier: Programming Language :: Python :: 3.11
Classifier: Programming Language :: Python :: 3.12
Classifier: Topic :: Database
Classifier: Topic :: Software Development :: Libraries :: Python Modules
Requires-Python: >=3.10
Requires-Dist: psycopg[binary]>=3.1
Requires-Dist: pydantic>=2.7
